searxng_mcp/__init__.py
searxng_mcp/api_docs.py
searxng_mcp/changelog.py
searxng_mcp/comparison.py
searxng_mcp/config.py
searxng_mcp/crawler.py
searxng_mcp/errors.py
searxng_mcp/extractor.py
searxng_mcp/github.py
searxng_mcp/images.py
searxng_mcp/registry.py
searxng_mcp/search.py
searxng_mcp/server.py
searxng_mcp/service_health.py
searxng_mcp/tracking.py
web_research_assistant-0.1.0.dist-info/licenses/LICENSE
web_research_assistant-0.1.0.dist-info/METADATA
web_research_assistant-0.1.0.dist-info/WHEEL
web_research_assistant-0.1.0.dist-info/entry_points.txt
web_research_assistant-0.1.0.dist-info/top_level.txt
web_research_assistant-0.1.0.dist-info/RECORD
