Metadata-Version: 2.4
Name: web-research-assistant
Version: 0.1.0
Summary: Comprehensive MCP server for web research with 13 tools: search, crawl, package info, GitHub stats, error translation, API docs discovery, and more.
Author-email: Elad Ben Haim <elad12390@gmail.com>
Maintainer-email: Elad Ben Haim <elad12390@gmail.com>
License: MIT
Project-URL: Homepage, https://github.com/elad12390/web-research-assistant
Project-URL: Repository, https://github.com/elad12390/web-research-assistant
Project-URL: Issues, https://github.com/elad12390/web-research-assistant/issues
Project-URL: Changelog, https://github.com/elad12390/web-research-assistant/blob/main/CHANGELOG.md
Keywords: mcp,model-context-protocol,searxng,web-research,ai-tools,claude,search,crawling,package-registry,github-api,error-translator,api-documentation
Classifier: Development Status :: 4 - Beta
Classifier: Intended Audience :: Developers
Classifier: License :: OSI Approved :: MIT License
Classifier: Programming Language :: Python :: 3
Classifier: Programming Language :: Python :: 3.10
Classifier: Programming Language :: Python :: 3.11
Classifier: Programming Language :: Python :: 3.12
Classifier: Programming Language :: Python :: 3.13
Classifier: Topic :: Software Development :: Libraries :: Python Modules
Classifier: Topic :: Internet :: WWW/HTTP :: Indexing/Search
Classifier: Topic :: Scientific/Engineering :: Artificial Intelligence
Requires-Python: >=3.10
License-File: LICENSE
Requires-Dist: mcp[cli]>=1.2.0
Requires-Dist: httpx<0.29,>=0.27
Requires-Dist: crawl4ai>=0.4.0
Requires-Dist: beautifulsoup4>=4.12.0
Provides-Extra: dev
Requires-Dist: pytest>=7.0.0; extra == "dev"
Requires-Dist: pytest-asyncio>=0.21.0; extra == "dev"
Requires-Dist: pytest-cov>=4.0.0; extra == "dev"
Requires-Dist: ruff>=0.1.0; extra == "dev"
Requires-Dist: mypy>=1.0.0; extra == "dev"
Dynamic: license-file
